ssi_pylint_odoo
