Metadata-Version: 1.1
Name: ssi-pylint-odoo
Version: 3.5.0.dev2
Summary: Pylint plugin for Odoo Development in Simetri Sinergi Indonesia
Home-page: https://github.com/simetri-sinergi-id/ssi-pylint-odoo
Author: PT. Simetri Sinergi Indonesia
Author-email: support@simetri-sinergi.id
License: APGL3
Platform: UNKNOWN
Classifier: Development Status :: 4 - Beta
Classifier: Environment :: Console
Classifier: Intended Audience :: Developers
Classifier: Intended Audience :: Information Technology
Classifier: License :: OSI Approved :: GNU Affero General Public License v3 or later (AGPLv3+)
Classifier: Operating System :: POSIX :: Linux
Classifier: Programming Language :: Python
